Compiled from "JavaStepDefinition.java"
class cucumber.runtime.java.JavaStepDefinition extends java.lang.Object implements cucumber.runtime.StepDefinition
  SourceFile: "JavaStepDefinition.java"
  minor version: 0
  major version: 50
  Constant pool:
const #1 = Method	#30.#89;	//  java/lang/Object."<init>":()V
const #2 = Field	#29.#90;	//  cucumber/runtime/java/JavaStepDefinition.method:Ljava/lang/reflect/Method;
const #3 = Method	#22.#91;	//  cucumber/runtime/ParameterType.fromMethod:(Ljava/lang/reflect/Method;)Ljava/util/List;
const #4 = Field	#29.#92;	//  cucumber/runtime/java/JavaStepDefinition.parameterTypes:Ljava/util/List;
const #5 = Field	#29.#93;	//  cucumber/runtime/java/JavaStepDefinition.pattern:Ljava/util/regex/Pattern;
const #6 = class	#94;	//  cucumber/runtime/JdkPatternArgumentMatcher
const #7 = Method	#6.#95;	//  cucumber/runtime/JdkPatternArgumentMatcher."<init>":(Ljava/util/regex/Pattern;)V
const #8 = Field	#29.#96;	//  cucumber/runtime/java/JavaStepDefinition.argumentMatcher:Lcucumber/runtime/JdkPatternArgumentMatcher;
const #9 = Field	#29.#97;	//  cucumber/runtime/java/JavaStepDefinition.timeout:I
const #10 = Field	#29.#98;	//  cucumber/runtime/java/JavaStepDefinition.objectFactory:Lcucumber/runtime/java/ObjectFactory;
const #11 = Method	#99.#100;	//  java/lang/reflect/Method.getDeclaringClass:()Ljava/lang/Class;
const #12 = InterfaceMethod	#101.#102;	//  cucumber/runtime/java/ObjectFactory.getInstance:(Ljava/lang/Class;)Ljava/lang/Object;
const #13 = Method	#103.#104;	//  cucumber/runtime/Utils.invoke:(Ljava/lang/Object;Ljava/lang/reflect/Method;I[Ljava/lang/Object;)Ljava/lang/Object;
const #14 = Method	#105.#106;	//  gherkin/formatter/model/Step.getName:()Ljava/lang/String;
const #15 = Method	#6.#107;	//  cucumber/runtime/JdkPatternArgumentMatcher.argumentsFrom:(Ljava/lang/String;)Ljava/util/List;
const #16 = Field	#108.#109;	//  cucumber/runtime/MethodFormat.FULL:Lcucumber/runtime/MethodFormat;
const #17 = Field	#108.#110;	//  cucumber/runtime/MethodFormat.SHORT:Lcucumber/runtime/MethodFormat;
const #18 = Method	#108.#111;	//  cucumber/runtime/MethodFormat.format:(Ljava/lang/reflect/Method;)Ljava/lang/String;
const #19 = InterfaceMethod	#112.#113;	//  java/util/List.size:()I
const #20 = Method	#114.#115;	//  java/lang/Integer.valueOf:(I)Ljava/lang/Integer;
const #21 = InterfaceMethod	#112.#116;	//  java/util/List.get:(I)Ljava/lang/Object;
const #22 = class	#117;	//  cucumber/runtime/ParameterType
const #23 = Method	#118.#119;	//  java/lang/StackTraceElement.getClassName:()Ljava/lang/String;
const #24 = Method	#120.#106;	//  java/lang/Class.getName:()Ljava/lang/String;
const #25 = Method	#121.#122;	//  java/lang/String.equals:(Ljava/lang/Object;)Z
const #26 = Method	#118.#123;	//  java/lang/StackTraceElement.getMethodName:()Ljava/lang/String;
const #27 = Method	#99.#106;	//  java/lang/reflect/Method.getName:()Ljava/lang/String;
const #28 = Method	#124.#125;	//  java/util/regex/Pattern.pattern:()Ljava/lang/String;
const #29 = class	#126;	//  cucumber/runtime/java/JavaStepDefinition
const #30 = class	#127;	//  java/lang/Object
const #31 = class	#128;	//  cucumber/runtime/StepDefinition
const #32 = Asciz	method;
const #33 = Asciz	Ljava/lang/reflect/Method;;
const #34 = Asciz	pattern;
const #35 = Asciz	Ljava/util/regex/Pattern;;
const #36 = Asciz	timeout;
const #37 = Asciz	I;
const #38 = Asciz	argumentMatcher;
const #39 = Asciz	Lcucumber/runtime/JdkPatternArgumentMatcher;;
const #40 = Asciz	objectFactory;
const #41 = Asciz	Lcucumber/runtime/java/ObjectFactory;;
const #42 = Asciz	parameterTypes;
const #43 = Asciz	Ljava/util/List;;
const #44 = Asciz	Signature;
const #45 = Asciz	Ljava/util/List<Lcucumber/runtime/ParameterType;>;;
const #46 = Asciz	<init>;
const #47 = Asciz	(Ljava/lang/reflect/Method;Ljava/util/regex/Pattern;ILcucumber/runtime/java/ObjectFactory;)V;
const #48 = Asciz	Code;
const #49 = Asciz	LineNumberTable;
const #50 = Asciz	LocalVariableTable;
const #51 = Asciz	this;
const #52 = Asciz	Lcucumber/runtime/java/JavaStepDefinition;;
const #53 = Asciz	execute;
const #54 = Asciz	(Lgherkin/I18n;[Ljava/lang/Object;)V;
const #55 = Asciz	i18n;
const #56 = Asciz	Lgherkin/I18n;;
const #57 = Asciz	args;
const #58 = Asciz	[Ljava/lang/Object;;
const #59 = Asciz	Exceptions;
const #60 = class	#129;	//  java/lang/Throwable
const #61 = Asciz	matchedArguments;
const #62 = Asciz	(Lgherkin/formatter/model/Step;)Ljava/util/List;;
const #63 = Asciz	step;
const #64 = Asciz	Lgherkin/formatter/model/Step;;
const #65 = Asciz	(Lgherkin/formatter/model/Step;)Ljava/util/List<Lgherkin/formatter/Argument;>;;
const #66 = Asciz	getLocation;
const #67 = Asciz	(Z)Ljava/lang/String;;
const #68 = Asciz	detail;
const #69 = Asciz	Z;
const #70 = Asciz	format;
const #71 = Asciz	Lcucumber/runtime/MethodFormat;;
const #72 = Asciz	StackMapTable;
const #73 = class	#130;	//  cucumber/runtime/MethodFormat
const #74 = Asciz	getParameterCount;
const #75 = Asciz	()Ljava/lang/Integer;;
const #76 = Asciz	getParameterType;
const #77 = Asciz	(ILjava/lang/reflect/Type;)Lcucumber/runtime/ParameterType;;
const #78 = Asciz	n;
const #79 = Asciz	argumentType;
const #80 = Asciz	Ljava/lang/reflect/Type;;
const #81 = Asciz	isDefinedAt;
const #82 = Asciz	(Ljava/lang/StackTraceElement;)Z;
const #83 = Asciz	e;
const #84 = Asciz	Ljava/lang/StackTraceElement;;
const #85 = Asciz	getPattern;
const #86 = Asciz	()Ljava/lang/String;;
const #87 = Asciz	SourceFile;
const #88 = Asciz	JavaStepDefinition.java;
const #89 = NameAndType	#46:#131;//  "<init>":()V
const #90 = NameAndType	#32:#33;//  method:Ljava/lang/reflect/Method;
const #91 = NameAndType	#132:#133;//  fromMethod:(Ljava/lang/reflect/Method;)Ljava/util/List;
const #92 = NameAndType	#42:#43;//  parameterTypes:Ljava/util/List;
const #93 = NameAndType	#34:#35;//  pattern:Ljava/util/regex/Pattern;
const #94 = Asciz	cucumber/runtime/JdkPatternArgumentMatcher;
const #95 = NameAndType	#46:#134;//  "<init>":(Ljava/util/regex/Pattern;)V
const #96 = NameAndType	#38:#39;//  argumentMatcher:Lcucumber/runtime/JdkPatternArgumentMatcher;
const #97 = NameAndType	#36:#37;//  timeout:I
const #98 = NameAndType	#40:#41;//  objectFactory:Lcucumber/runtime/java/ObjectFactory;
const #99 = class	#135;	//  java/lang/reflect/Method
const #100 = NameAndType	#136:#137;//  getDeclaringClass:()Ljava/lang/Class;
const #101 = class	#138;	//  cucumber/runtime/java/ObjectFactory
const #102 = NameAndType	#139:#140;//  getInstance:(Ljava/lang/Class;)Ljava/lang/Object;
const #103 = class	#141;	//  cucumber/runtime/Utils
const #104 = NameAndType	#142:#143;//  invoke:(Ljava/lang/Object;Ljava/lang/reflect/Method;I[Ljava/lang/Object;)Ljava/lang/Object;
const #105 = class	#144;	//  gherkin/formatter/model/Step
const #106 = NameAndType	#145:#86;//  getName:()Ljava/lang/String;
const #107 = NameAndType	#146:#147;//  argumentsFrom:(Ljava/lang/String;)Ljava/util/List;
const #108 = class	#130;	//  cucumber/runtime/MethodFormat
const #109 = NameAndType	#148:#71;//  FULL:Lcucumber/runtime/MethodFormat;
const #110 = NameAndType	#149:#71;//  SHORT:Lcucumber/runtime/MethodFormat;
const #111 = NameAndType	#70:#150;//  format:(Ljava/lang/reflect/Method;)Ljava/lang/String;
const #112 = class	#151;	//  java/util/List
const #113 = NameAndType	#152:#153;//  size:()I
const #114 = class	#154;	//  java/lang/Integer
const #115 = NameAndType	#155:#156;//  valueOf:(I)Ljava/lang/Integer;
const #116 = NameAndType	#157:#158;//  get:(I)Ljava/lang/Object;
const #117 = Asciz	cucumber/runtime/ParameterType;
const #118 = class	#159;	//  java/lang/StackTraceElement
const #119 = NameAndType	#160:#86;//  getClassName:()Ljava/lang/String;
const #120 = class	#161;	//  java/lang/Class
const #121 = class	#162;	//  java/lang/String
const #122 = NameAndType	#163:#164;//  equals:(Ljava/lang/Object;)Z
const #123 = NameAndType	#165:#86;//  getMethodName:()Ljava/lang/String;
const #124 = class	#166;	//  java/util/regex/Pattern
const #125 = NameAndType	#34:#86;//  pattern:()Ljava/lang/String;
const #126 = Asciz	cucumber/runtime/java/JavaStepDefinition;
const #127 = Asciz	java/lang/Object;
const #128 = Asciz	cucumber/runtime/StepDefinition;
const #129 = Asciz	java/lang/Throwable;
const #130 = Asciz	cucumber/runtime/MethodFormat;
const #131 = Asciz	()V;
const #132 = Asciz	fromMethod;
const #133 = Asciz	(Ljava/lang/reflect/Method;)Ljava/util/List;;
const #134 = Asciz	(Ljava/util/regex/Pattern;)V;
const #135 = Asciz	java/lang/reflect/Method;
const #136 = Asciz	getDeclaringClass;
const #137 = Asciz	()Ljava/lang/Class;;
const #138 = Asciz	cucumber/runtime/java/ObjectFactory;
const #139 = Asciz	getInstance;
const #140 = Asciz	(Ljava/lang/Class;)Ljava/lang/Object;;
const #141 = Asciz	cucumber/runtime/Utils;
const #142 = Asciz	invoke;
const #143 = Asciz	(Ljava/lang/Object;Ljava/lang/reflect/Method;I[Ljava/lang/Object;)Ljava/lang/Object;;
const #144 = Asciz	gherkin/formatter/model/Step;
const #145 = Asciz	getName;
const #146 = Asciz	argumentsFrom;
const #147 = Asciz	(Ljava/lang/String;)Ljava/util/List;;
const #148 = Asciz	FULL;
const #149 = Asciz	SHORT;
const #150 = Asciz	(Ljava/lang/reflect/Method;)Ljava/lang/String;;
const #151 = Asciz	java/util/List;
const #152 = Asciz	size;
const #153 = Asciz	()I;
const #154 = Asciz	java/lang/Integer;
const #155 = Asciz	valueOf;
const #156 = Asciz	(I)Ljava/lang/Integer;;
const #157 = Asciz	get;
const #158 = Asciz	(I)Ljava/lang/Object;;
const #159 = Asciz	java/lang/StackTraceElement;
const #160 = Asciz	getClassName;
const #161 = Asciz	java/lang/Class;
const #162 = Asciz	java/lang/String;
const #163 = Asciz	equals;
const #164 = Asciz	(Ljava/lang/Object;)Z;
const #165 = Asciz	getMethodName;
const #166 = Asciz	java/util/regex/Pattern;

{
public cucumber.runtime.java.JavaStepDefinition(java.lang.reflect.Method, java.util.regex.Pattern, int, cucumber.runtime.java.ObjectFactory);
  Code:
   Stack=4, Locals=5, Args_size=5
   0:	aload_0
   1:	invokespecial	#1; //Method java/lang/Object."<init>":()V
   4:	aload_0
   5:	aload_1
   6:	putfield	#2; //Field method:Ljava/lang/reflect/Method;
   9:	aload_0
   10:	aload_1
   11:	invokestatic	#3; //Method cucumber/runtime/ParameterType.fromMethod:(Ljava/lang/reflect/Method;)Ljava/util/List;
   14:	putfield	#4; //Field parameterTypes:Ljava/util/List;
   17:	aload_0
   18:	aload_2
   19:	putfield	#5; //Field pattern:Ljava/util/regex/Pattern;
   22:	aload_0
   23:	new	#6; //class cucumber/runtime/JdkPatternArgumentMatcher
   26:	dup
   27:	aload_2
   28:	invokespecial	#7; //Method cucumber/runtime/JdkPatternArgumentMatcher."<init>":(Ljava/util/regex/Pattern;)V
   31:	putfield	#8; //Field argumentMatcher:Lcucumber/runtime/JdkPatternArgumentMatcher;
   34:	aload_0
   35:	iload_3
   36:	putfield	#9; //Field timeout:I
   39:	aload_0
   40:	aload	4
   42:	putfield	#10; //Field objectFactory:Lcucumber/runtime/java/ObjectFactory;
   45:	return
  LineNumberTable: 
   line 25: 0
   line 26: 4
   line 27: 9
   line 28: 17
   line 29: 22
   line 30: 34
   line 31: 39
   line 32: 45

  LocalVariableTable: 
   Start  Length  Slot  Name   Signature
   0      46      0    this       Lcucumber/runtime/java/JavaStepDefinition;
   0      46      1    method       Ljava/lang/reflect/Method;
   0      46      2    pattern       Ljava/util/regex/Pattern;
   0      46      3    timeout       I
   0      46      4    objectFactory       Lcucumber/runtime/java/ObjectFactory;


public void execute(gherkin.I18n, java.lang.Object[])   throws java.lang.Throwable;
  Code:
   Stack=4, Locals=3, Args_size=3
   0:	aload_0
   1:	getfield	#10; //Field objectFactory:Lcucumber/runtime/java/ObjectFactory;
   4:	aload_0
   5:	getfield	#2; //Field method:Ljava/lang/reflect/Method;
   8:	invokevirtual	#11; //Method java/lang/reflect/Method.getDeclaringClass:()Ljava/lang/Class;
   11:	invokeinterface	#12,  2; //InterfaceMethod cucumber/runtime/java/ObjectFactory.getInstance:(Ljava/lang/Class;)Ljava/lang/Object;
   16:	aload_0
   17:	getfield	#2; //Field method:Ljava/lang/reflect/Method;
   20:	aload_0
   21:	getfield	#9; //Field timeout:I
   24:	aload_2
   25:	invokestatic	#13; //Method cucumber/runtime/Utils.invoke:(Ljava/lang/Object;Ljava/lang/reflect/Method;I[Ljava/lang/Object;)Ljava/lang/Object;
   28:	pop
   29:	return
  LineNumberTable: 
   line 35: 0
   line 36: 29

  LocalVariableTable: 
   Start  Length  Slot  Name   Signature
   0      30      0    this       Lcucumber/runtime/java/JavaStepDefinition;
   0      30      1    i18n       Lgherkin/I18n;
   0      30      2    args       [Ljava/lang/Object;

  Exceptions: 
   throws java.lang.Throwable
public java.util.List matchedArguments(gherkin.formatter.model.Step);
  Code:
   Stack=2, Locals=2, Args_size=2
   0:	aload_0
   1:	getfield	#8; //Field argumentMatcher:Lcucumber/runtime/JdkPatternArgumentMatcher;
   4:	aload_1
   5:	invokevirtual	#14; //Method gherkin/formatter/model/Step.getName:()Ljava/lang/String;
   8:	invokevirtual	#15; //Method cucumber/runtime/JdkPatternArgumentMatcher.argumentsFrom:(Ljava/lang/String;)Ljava/util/List;
   11:	areturn
  LineNumberTable: 
   line 39: 0

  LocalVariableTable: 
   Start  Length  Slot  Name   Signature
   0      12      0    this       Lcucumber/runtime/java/JavaStepDefinition;
   0      12      1    step       Lgherkin/formatter/model/Step;

  Signature: length = 0x2
   00 41 

public java.lang.String getLocation(boolean);
  Code:
   Stack=2, Locals=3, Args_size=2
   0:	iload_1
   1:	ifeq	10
   4:	getstatic	#16; //Field cucumber/runtime/MethodFormat.FULL:Lcucumber/runtime/MethodFormat;
   7:	goto	13
   10:	getstatic	#17; //Field cucumber/runtime/MethodFormat.SHORT:Lcucumber/runtime/MethodFormat;
   13:	astore_2
   14:	aload_2
   15:	aload_0
   16:	getfield	#2; //Field method:Ljava/lang/reflect/Method;
   19:	invokevirtual	#18; //Method cucumber/runtime/MethodFormat.format:(Ljava/lang/reflect/Method;)Ljava/lang/String;
   22:	areturn
  LineNumberTable: 
   line 43: 0
   line 44: 14

  LocalVariableTable: 
   Start  Length  Slot  Name   Signature
   0      23      0    this       Lcucumber/runtime/java/JavaStepDefinition;
   0      23      1    detail       Z
   14      9      2    format       Lcucumber/runtime/MethodFormat;

  StackMapTable: number_of_entries = 2
   frame_type = 10 /* same */
   frame_type = 66 /* same_locals_1_stack_item */
     stack = [ class cucumber/runtime/MethodFormat ]


public java.lang.Integer getParameterCount();
  Code:
   Stack=1, Locals=1, Args_size=1
   0:	aload_0
   1:	getfield	#4; //Field parameterTypes:Ljava/util/List;
   4:	invokeinterface	#19,  1; //InterfaceMethod java/util/List.size:()I
   9:	invokestatic	#20; //Method java/lang/Integer.valueOf:(I)Ljava/lang/Integer;
   12:	areturn
  LineNumberTable: 
   line 49: 0

  LocalVariableTable: 
   Start  Length  Slot  Name   Signature
   0      13      0    this       Lcucumber/runtime/java/JavaStepDefinition;


public cucumber.runtime.ParameterType getParameterType(int, java.lang.reflect.Type);
  Code:
   Stack=2, Locals=3, Args_size=3
   0:	aload_0
   1:	getfield	#4; //Field parameterTypes:Ljava/util/List;
   4:	iload_1
   5:	invokeinterface	#21,  2; //InterfaceMethod java/util/List.get:(I)Ljava/lang/Object;
   10:	checkcast	#22; //class cucumber/runtime/ParameterType
   13:	areturn
  LineNumberTable: 
   line 54: 0

  LocalVariableTable: 
   Start  Length  Slot  Name   Signature
   0      14      0    this       Lcucumber/runtime/java/JavaStepDefinition;
   0      14      1    n       I
   0      14      2    argumentType       Ljava/lang/reflect/Type;


public boolean isDefinedAt(java.lang.StackTraceElement);
  Code:
   Stack=2, Locals=2, Args_size=2
   0:	aload_1
   1:	invokevirtual	#23; //Method java/lang/StackTraceElement.getClassName:()Ljava/lang/String;
   4:	aload_0
   5:	getfield	#2; //Field method:Ljava/lang/reflect/Method;
   8:	invokevirtual	#11; //Method java/lang/reflect/Method.getDeclaringClass:()Ljava/lang/Class;
   11:	invokevirtual	#24; //Method java/lang/Class.getName:()Ljava/lang/String;
   14:	invokevirtual	#25; //Method java/lang/String.equals:(Ljava/lang/Object;)Z
   17:	ifeq	41
   20:	aload_1
   21:	invokevirtual	#26; //Method java/lang/StackTraceElement.getMethodName:()Ljava/lang/String;
   24:	aload_0
   25:	getfield	#2; //Field method:Ljava/lang/reflect/Method;
   28:	invokevirtual	#27; //Method java/lang/reflect/Method.getName:()Ljava/lang/String;
   31:	invokevirtual	#25; //Method java/lang/String.equals:(Ljava/lang/Object;)Z
   34:	ifeq	41
   37:	iconst_1
   38:	goto	42
   41:	iconst_0
   42:	ireturn
  LineNumberTable: 
   line 58: 0

  LocalVariableTable: 
   Start  Length  Slot  Name   Signature
   0      43      0    this       Lcucumber/runtime/java/JavaStepDefinition;
   0      43      1    e       Ljava/lang/StackTraceElement;

  StackMapTable: number_of_entries = 2
   frame_type = 41 /* same */
   frame_type = 64 /* same_locals_1_stack_item */
     stack = [ int ]


public java.lang.String getPattern();
  Code:
   Stack=1, Locals=1, Args_size=1
   0:	aload_0
   1:	getfield	#5; //Field pattern:Ljava/util/regex/Pattern;
   4:	invokevirtual	#28; //Method java/util/regex/Pattern.pattern:()Ljava/lang/String;
   7:	areturn
  LineNumberTable: 
   line 63: 0

  LocalVariableTable: 
   Start  Length  Slot  Name   Signature
   0      8      0    this       Lcucumber/runtime/java/JavaStepDefinition;


}

